LICENSE
README.md
pyproject.toml
setup.py
src/cocotb_TileLink/__init__.py
src/cocotb_TileLink/_version.py
src/cocotb_TileLink.egg-info/PKG-INFO
src/cocotb_TileLink.egg-info/SOURCES.txt
src/cocotb_TileLink.egg-info/dependency_links.txt
src/cocotb_TileLink.egg-info/requires.txt
src/cocotb_TileLink.egg-info/top_level.txt
src/cocotb_TileLink/TileLink_common/Interfaces.py
src/cocotb_TileLink/TileLink_common/MonitorInterfaces.py
src/cocotb_TileLink/TileLink_common/TileLink_types.py
src/cocotb_TileLink/TileLink_common/__init__.py
src/cocotb_TileLink/drivers/DutMasterMultiSlaveUL.py
src/cocotb_TileLink/drivers/DutMultiMasterMultiSlaveBridgeUL.py
src/cocotb_TileLink/drivers/DutMultiMasterSlaveUL.py
src/cocotb_TileLink/drivers/SimCheckInvalidSlaveUL.py
src/cocotb_TileLink/drivers/SimRandomTrafficGeneratorUL.py
src/cocotb_TileLink/drivers/SimSimpleMasterUL.py
src/cocotb_TileLink/drivers/SimSimpleSlaveUL.py
src/cocotb_TileLink/drivers/SimTrafficGeneratorUL.py
src/cocotb_TileLink/drivers/__init__.py
src/cocotb_TileLink/monitors/TileLinkULMonitor.py
src/cocotb_TileLink/monitors/__init__.py